tailwiz/__init__.py
tailwiz/list_tasks.py
tailwiz/tasks/__init__.py
tailwiz/tasks/classify.py
tailwiz/tasks/generate.py
tailwiz/tasks/parse.py
tailwiz/tasks/task.py
tailwiz/tasks/utils.py
tailwiz-0.0.24.dist-info/LICENSE
tailwiz-0.0.24.dist-info/METADATA
tailwiz-0.0.24.dist-info/WHEEL
tailwiz-0.0.24.dist-info/top_level.txt
tailwiz-0.0.24.dist-info/RECORD
