Metadata-Version: 2.1
Name: tailwiz
Version: 0.0.24
Home-page: https://github.com/timothydai/tailwiz
Author: Timothy Dai
Author-email: timdai@stanford.edu
Classifier: Development Status :: 2 - Pre-Alpha
Classifier: Programming Language :: Python :: 3
Classifier: Programming Language :: Python :: 3.7
Classifier: License :: OSI Approved :: MIT License
Classifier: Operating System :: OS Independent
License-File: LICENSE
Requires-Dist: scikit-learn
Requires-Dist: transformers
Requires-Dist: evaluate
Requires-Dist: pandas
Requires-Dist: torch
Requires-Dist: numpy
Requires-Dist: sentencepiece
Requires-Dist: accelerate
